setup.cfg
setup.py
coloured_terminal/__init__.py
coloured_terminal/terminal.py
coloured_terminal/проверка_элементов.py
coloured_terminal/работа_с_файлами.py
coloured_terminal.egg-info/PKG-INFO
coloured_terminal.egg-info/SOURCES.txt
coloured_terminal.egg-info/dependency_links.txt
coloured_terminal.egg-info/not-zip-safe
coloured_terminal.egg-info/top_level.txt