Metadata-Version: 2.1
Name: coloured-terminal
Version: 0.3
Summary: Писать цветными буквами в терминале
Author-email: nikitastrukalin747@icloud.com
